configure_vm_image/__init__.py
configure_vm_image/_version.py
configure_vm_image/configure.py
configure_vm_image/cli/__init__.py
configure_vm_image/cli/configure_image.py
configure_vm_image/cli/corc.py
configure_vm_image/cli/helpers.py
configure_vm_image/cli/input_groups/__init__.py
configure_vm_image/cli/input_groups/configure.py
configure_vm_image/cli/operations/__init__.py
configure_vm_image/cli/operations/configure.py
configure_vm_image/cli/parsers/__init__.py
configure_vm_image/cli/parsers/actions.py
configure_vm_image/cli/parsers/configure.py
configure_vm_image/common/__init__.py
configure_vm_image/common/codes.py
configure_vm_image/common/defaults.py
configure_vm_image/common/utils.py
configure_vm_image/utils/__init__.py
configure_vm_image/utils/io.py
configure_vm_image/utils/job.py
tests/__init__.py
tests/context.py
tests/test_cli_base.py
tests/test_cli_configure_vm_image.py
tests/test_image_configure.py
configure_vm_image-0.1.2.dist-info/METADATA
configure_vm_image-0.1.2.dist-info/WHEEL
configure_vm_image-0.1.2.dist-info/entry_points.txt
configure_vm_image-0.1.2.dist-info/top_level.txt
configure_vm_image-0.1.2.dist-info/RECORD
