Metadata-Version: 2.2
Name: configure-vm-image
Version: 0.1.2
Summary: This tool can be used for configuring virtual machine images.
Home-page: https://github.com/rasmunk/configure-vm-image
Author: Rasmus Munk
Author-email: munk1@live.dk
License: MIT
Keywords: Virtual Machine,VM,Images
Classifier: Intended Audience :: Developers
Classifier: Intended Audience :: System Administrators
Classifier: Programming Language :: Python
Classifier: Programming Language :: Python :: 3.8
Classifier: Programming Language :: Python :: 3.9
Classifier: Programming Language :: Python :: 3.10
Classifier: Programming Language :: Python :: 3.11
Classifier: Programming Language :: Python :: 3.12
Requires-Dist: argparse
Requires-Dist: libvirt-provider>=0.0.1
Provides-Extra: dev
Requires-Dist: black==24.3.0; extra == "dev"
Requires-Dist: docutils==0.18.1; extra == "dev"
Requires-Dist: flake8==6.0.0; extra == "dev"
Dynamic: author
Dynamic: author-email
Dynamic: classifier
Dynamic: description
Dynamic: description-content-type
Dynamic: home-page
Dynamic: keywords
Dynamic: license
Dynamic: provides-extra
Dynamic: requires-dist
Dynamic: summary
